odoo9_addon_geoengine_maplausanne-9.0.1.0.0-py2.7-nspkg.pth
odoo9_addon_geoengine_maplausanne-9.0.1.0.0.dist-info/top_level.txt
odoo9_addon_geoengine_maplausanne-9.0.1.0.0.dist-info/WHEEL
odoo9_addon_geoengine_maplausanne-9.0.1.0.0.dist-info/RECORD
odoo9_addon_geoengine_maplausanne-9.0.1.0.0.dist-info/metadata.json
odoo9_addon_geoengine_maplausanne-9.0.1.0.0.dist-info/DESCRIPTION.rst
odoo9_addon_geoengine_maplausanne-9.0.1.0.0.dist-info/METADATA
odoo9_addon_geoengine_maplausanne-9.0.1.0.0.dist-info/namespace_packages.txt
odoo_addons/geoengine_maplausanne/__openerp__.py
odoo_addons/geoengine_maplausanne/__init__.py
odoo_addons/geoengine_maplausanne/models/geo_raster_layer.py
odoo_addons/geoengine_maplausanne/models/__init__.py
odoo_addons/geoengine_maplausanne/data/geo_raster_layer_type.xml
